topsis_py/__init__.py
topsis_py/topsis.py
topsis_py/topsis_cmd.py
TOPSIS_Saumyaa_101803609-0.0.9.dist-info/LICENSE
TOPSIS_Saumyaa_101803609-0.0.9.dist-info/METADATA
TOPSIS_Saumyaa_101803609-0.0.9.dist-info/WHEEL
TOPSIS_Saumyaa_101803609-0.0.9.dist-info/entry_points.txt
TOPSIS_Saumyaa_101803609-0.0.9.dist-info/top_level.txt
TOPSIS_Saumyaa_101803609-0.0.9.dist-info/RECORD
