Metadata-Version: 2.1
Name: TOPSIS-Saumyaa-101803609
Version: 0.0.9
Summary: topsis package
Home-page: https://github.com/pypa/sampleproject
Author: Saumyaa Mathur
Author-email: saumyaamathur27@gmail.com
License: MIT
Platform: UNKNOWN
Classifier: Programming Language :: Python :: 3
Classifier: License :: OSI Approved :: MIT License
Classifier: Operating System :: OS Independent
Requires-Python: >=3.6
Requires-Dist: pandas
Requires-Dist: statistics
